{
  "job_titles": [
    "software engineer",
    "software developer",
    "backend engineer",
    "frontend engineer",
    "full stack engineer",
    "full stack developer",
    "swe",
    "associate engineer",
    "junior engineer",
    "junior developer",
    "engineer i",
    "software engineer i",
    "entry level engineer"
  ],
  "ignore_titles": [
    "senior",
    "staff",
    "principal",
    "lead",
    "manager",
    "director",
    "vp",
    "head of",
    "architect",
    "distinguished",
    "fellow"
  ],
  "countries": ["usa", "united states", "remote", "us"],
  "states": [
    "california", "new york", "texas", "washington", "massachusetts",
    "illinois", "georgia", "colorado", "florida", "virginia"
  ],
  "states_abbr": ["ca", "ny", "tx", "wa", "ma", "il", "ga", "co", "fl", "va"],
  "posting_diff": 7
}
